{
  "dxt_version": "0.1.0",
  "name": "kukapay__pancakeswap-poolspy-mcp",
  "display_name": "pancakeswap-poolspy-mcp",
  "version": "1.0.0",
  "description": "An MCP server that tracks newly created liquidity pools on Pancake Swap",
  "author": {
    "name": "kukapay"
  },
  "server": {
    "type": "python",
    "entry_point": "index.js",
    "mcp_config": {
      "command": "unknown",
      "args": [],
      "env": {}
    }
  },
  "tools": [],
  "prompts": [],
  "keywords": [],
  "user_config": {},
  "readme": "# PancakeSwap PoolSpy MCP Server\n\nAn MCP server that tracks newly created liquidity pools on Pancake Swap, providing real-time data for DeFi analysts, traders, and developers.\n\n[![License](https://img.shields.io/badge/License-MIT-blue.svg)](https://opensource.org/licenses/MIT)\n[![Python](https://img.shields.io/badge/Python-3.10+-yellow.svg)](https://www.python.org/)\n[![smithery badge](https://smithery.ai/badge/@kukapay/pancakeswap-poolspy-mcp)](https://smithery.ai/server/@kukapay/pancakeswap-poolspy-mcp)\n\n## Features\n\n- **Real-Time Pool Tracking**: Fetches pools created within a specified time range (default: 5 minutes).\n- **Customizable Queries**: Adjust the time range (in seconds) and the number of pools returned (default: 100).\n- **Detailed Metrics**: Includes pool address, tokens, creation timestamp, block number, transaction count, volume (USD), and total value locked (USD).\n\n## Prerequisites\n\n- **Python 3.10+**: Ensure Python is installed on your system.\n- **The Graph API Key**: Obtain an API key from [The Graph](https://thegraph.com/) to access the PancakeSwap subgraph.\n\n## Installation\n\n### Installing via Smithery\n\nTo install PancakeSwap PoolSpy for Claude Desktop automatically via [Smithery](https://smithery.ai/server/@kukapay/pancakeswap-poolspy-mcp):\n\n```bash\nnpx -y @smithery/cli install @kukapay/pancakeswap-poolspy-mcp --client claude\n```\n\n1. **Clone the Repository**:\n   ```bash\n   git clone https://github.com/kukapay/pancakeswap-poolspy-mcp.git\n   cd pancakeswap-poolspy-mcp\n   ```\n\n2. **Install Dependencies**:\n   Install the required Python packages using uv:\n   ```bash\n   uv add mcp[cli] httpx dotenv\n   ```\n\n3. **Client Configuration**\n    ```json\n    {\n      \"mcpServers\": {\n        \"PancakeSwap-PoolSpy\": {\n          \"command\": \"uv\",\n          \"args\": [\"--directory\", \"path/to/pancakeswap-poolspy-mcp\", \"run\", \"main.py\"],\n          \"env\": {\n            \"THEGRAPH_API_KEY\": \"your api key from The Graph\"\n          }\n        }\n      }\n    }\n    ```\n\n## Usage\n\n### Running the Server\n\nRun the server in development mode to test it locally:\n```bash\nmcp dev main.py\n```\nThis launches the MCP Inspector, where you can interact with the `get_new_pools_bsc` tool.\n\n### Available Tool\n\n#### `get_new_pools_bsc(time_range_seconds: int = 300, limit: int = 100)`\n\nFetches a list of newly created PancakeSwap pools on BNB Smart Chain.\n\n- **Parameters**:\n  - `time_range_seconds` (int): Time range in seconds to look back for new pools. Default is 300 seconds (5 minutes).\n  - `limit` (int): Maximum number of pools to return. Default is 100 pools.\n\n- **Returns**: A formatted string listing pool details or an error message if the query fails.\n\n- **Example Outputs**:\n  - Default (last 5 minutes, up to 100 pools):\n    ```bash\n    get_new_pools_bsc()\n    ```\n    ```\n    Newly Created Trading Pools (Last 5 Minutes, Limit: 100):\n    Pool Address: 0x1234...5678\n    Tokens: WETH/USDC\n    Created At: 2025-03-16 12:00:00 UTC\n    Block Number: 12345678\n    Transaction Count: 10\n    Volume (USD): 1234.56\n    Total Value Locked (USD): 5678.90\n\n    Pool Address: 0x9abc...def0\n    Tokens: CAKE/BNB\n    Created At: 2025-03-16 12:01:00 UTC\n    Block Number: 12345679\n    Transaction Count: 5\n    Volume (USD): 789.12\n    Total Value Locked (USD): 3456.78\n    ```\n\n  - Custom (last 10 minutes, up to 50 pools):\n    ```bash\n    get_new_pools(600, 50)\n    ```\n    ```\n    Newly Created Trading Pools (Last 10 Minutes, Limit: 50):\n    [pool details...]\n    ```\n\n### **Example Prompts**:\n\n   - \"list newly created PancakeSwap pools from the last 1 hours.\"\n   - \"Display PancakeSwap pools created within the last 2 minutes.\"\n\n## License\n\nThis project is licensed under the MIT License. See the [LICENSE](LICENSE) file for details.\n",
  "category": "Finance",
  "quality_score": 42,
  "archestra_config": {
    "client_config_permutations": {
      "mcpServers": {
        "PancakeSwap-PoolSpy": {
          "command": "uv",
          "args": [
            "--directory",
            "path/to/pancakeswap-poolspy-mcp",
            "run",
            "main.py"
          ],
          "env": {
            "THEGRAPH_API_KEY": "your api key from The Graph"
          }
        },
        "PancakeSwap-PoolSpy-dev": {
          "command": "mcp",
          "args": [
            "dev",
            "main.py"
          ],
          "env": {}
        }
      }
    },
    "oauth": {
      "provider": null,
      "required": false
    }
  },
  "github_info": {
    "owner": "kukapay",
    "repo": "pancakeswap-poolspy-mcp",
    "url": "https://github.com/kukapay/pancakeswap-poolspy-mcp",
    "name": "pancakeswap-poolspy-mcp",
    "path": null,
    "stars": 5,
    "contributors": 2,
    "issues": 2,
    "releases": false,
    "ci_cd": false,
    "latest_commit_hash": "533e34308f3cbf8528e079c76dd3a6b53d5c4d3d"
  },
  "programming_language": "Python",
  "framework": null,
  "last_scraped_at": "2025-08-03T20:12:44.893Z",
  "evaluation_model": "gemini-2.5-flash",
  "protocol_features": {
    "implementing_tools": true,
    "implementing_prompts": false,
    "implementing_resources": false,
    "implementing_sampling": false,
    "implementing_roots": false,
    "implementing_logging": false,
    "implementing_stdio": true,
    "implementing_streamable_http": false,
    "implementing_oauth2": false
  },
  "dependencies": [
    {
      "name": "mcp",
      "importance": 10
    },
    {
      "name": "httpx",
      "importance": 7
    },
    {
      "name": "dotenv",
      "importance": 4
    }
  ],
  "raw_dependencies": "=== pyproject.toml ===\n[project]\nname = \"pancakeswap-poolspy-mcp\"\nversion = \"0.1.0\"\ndescription = \"An MCP server that tracks newly created liquidity pools on Pancake Swap\"\nreadme = \"README.md\"\nrequires-python = \">=3.13\"\ndependencies = [\n    \"dotenv>=0.9.9\",\n    \"httpx>=0.28.1\",\n    \"mcp[cli]>=1.4.1\",\n]\n"
}