{
  "dxt_version": "0.1.0",
  "name": "sapientpants__sonarqube-mcp-server",
  "display_name": "sonarqube-mcp-server",
  "version": "1.0.0",
  "description": "Model Context Protocol (MCP) server for SonarQube",
  "author": {
    "name": "sapientpants"
  },
  "server": {
    "type": "node",
    "entry_point": "index.js",
    "mcp_config": {
      "command": "unknown",
      "args": [],
      "env": {}
    }
  },
  "tools": [],
  "prompts": [],
  "keywords": [],
  "user_config": {},
  "readme": "# SonarQube MCP Server\n\n[![CI](https://github.com/sapientpants/sonarqube-mcp-server/actions/workflows/ci.yml/badge.svg)](https://github.com/sapientpants/sonarqube-mcp-server/actions/workflows/ci.yml)\n[![Quality Gate Status](https://sonarcloud.io/api/project_badges/measure?project=sonarqube-mcp-server&metric=alert_status)](https://sonarcloud.io/summary/new_code?id=sonarqube-mcp-server)\n[![Bugs](https://sonarcloud.io/api/project_badges/measure?project=sonarqube-mcp-server&metric=bugs)](https://sonarcloud.io/summary/new_code?id=sonarqube-mcp-server)\n[![Code Smells](https://sonarcloud.io/api/project_badges/measure?project=sonarqube-mcp-server&metric=code_smells)](https://sonarcloud.io/summary/new_code?id=sonarqube-mcp-server)\n[![Coverage](https://sonarcloud.io/api/project_badges/measure?project=sonarqube-mcp-server&metric=coverage)](https://sonarcloud.io/summary/new_code?id=sonarqube-mcp-server)\n[![Duplicated Lines (%)](https://sonarcloud.io/api/project_badges/measure?project=sonarqube-mcp-server&metric=duplicated_lines_density)](https://sonarcloud.io/summary/new_code?id=sonarqube-mcp-server)\n[![npm version](https://img.shields.io/npm/v/sonarqube-mcp-server.svg)](https://www.npmjs.com/package/sonarqube-mcp-server)\n[![npm downloads](https://img.shields.io/npm/dm/sonarqube-mcp-server.svg)](https://www.npmjs.com/package/sonarqube-mcp-server)\n[![License](https://img.shields.io/npm/l/sonarqube-mcp-server.svg)](https://github.com/sapientpants/sonarqube-mcp-server/blob/main/LICENSE)\n\nA Model Context Protocol (MCP) server that integrates with SonarQube to provide AI assistants with access to code quality metrics, issues, and analysis results.\n\n## Table of Contents\n\n- [Overview](#overview)\n- [Documentation](#documentation)\n- [Compatibility](#compatibility)\n- [Quick Start](#quick-start)\n- [Installation](#installation)\n  - [NPX](#npx-recommended)\n  - [Docker](#docker-recommended-for-production)\n  - [Local Development](#local-development)\n- [Configuration](#configuration)\n  - [Environment Variables](#environment-variables)\n  - [Authentication Methods](#authentication-methods)\n- [Available Tools](#available-tools)\n- [Usage Examples](#usage-examples)\n- [Architecture](#architecture)\n- [Development](#development)\n- [Troubleshooting](#troubleshooting)\n- [Contributing](#contributing)\n- [License](#license)\n- [External Resources](#external-resources)\n\n## Overview\n\nThe SonarQube MCP Server enables AI assistants to interact with SonarQube's code quality analysis capabilities through the Model Context Protocol. This integration allows AI assistants to:\n\n- 📊 **Retrieve code metrics and analysis results** - Access detailed quality metrics for your projects\n- 🐛 **Access and filter issues** - Search and filter code issues by severity, type, status, and more\n- 🔒 **Review security hotspots** - Find and manage security vulnerabilities with dedicated workflows\n- 🌿 **Analyze branches and PRs** - Review code quality in feature branches and pull requests\n- 📦 **Multi-project analysis** - Query issues and metrics across multiple projects simultaneously\n- ✅ **Check quality gates** - Monitor whether projects meet quality standards\n- 📈 **Analyze project quality over time** - Track metrics history and trends\n- 🔍 **View source code with issues** - See problematic code with highlighted issues\n- 🏥 **Monitor system health** - Check SonarQube instance status and availability\n- 🔄 **Enhanced error handling** - Clear error messages with solutions and automatic retry for transient failures\n\n## Documentation\n\n### Core Guides\n- **[Architecture Guide](docs/architecture.md)** - System architecture, design decisions, and component overview\n- **[Troubleshooting Guide](docs/troubleshooting.md)** - Common issues, debugging, and solutions\n\n### Security & Authentication\n- **[Security Guide](docs/security.md)** - Authentication, authorization, and security best practices\n\n## Compatibility\n\nFor detailed information about MCP protocol version support and SDK compatibility, see [COMPATIBILITY.md](COMPATIBILITY.md).\n\n## Quick Start\n\n### Prerequisites\n\n- [Claude Desktop](https://claude.ai/download) installed\n- A SonarQube instance or [SonarCloud](https://sonarcloud.io) account\n- A SonarQube/SonarCloud authentication token\n\n### 1. Get Your SonarQube Token\n\n**For SonarCloud:**\n1. Log in to [SonarCloud](https://sonarcloud.io)\n2. Go to **My Account** → **Security**\n3. Generate a new token\n\n**For SonarQube:**\n1. Log in to your SonarQube instance\n2. Go to **My Account** → **Security**\n3. Generate a new token\n\n### 2. Configure Claude Desktop\n\n1. Open Claude Desktop\n2. Go to **Settings** → **Developer** → **Edit Config**\n3. Add the SonarQube server configuration:\n\n```json\n{\n  \"mcpServers\": {\n    \"sonarqube\": {\n      \"command\": \"npx\",\n      \"args\": [\"-y\", \"sonarqube-mcp-server@latest\"],\n      \"env\": {\n        \"SONARQUBE_URL\": \"https://sonarcloud.io\",\n        \"SONARQUBE_TOKEN\": \"your-token-here\",\n        \"SONARQUBE_ORGANIZATION\": \"your-org (for SonarCloud)\"\n      }\n    }\n  }\n}\n```\n\n**Alternative authentication methods:**\n\nUsing Basic Authentication:\n```json\n{\n  \"mcpServers\": {\n    \"sonarqube\": {\n      \"command\": \"npx\",\n      \"args\": [\"-y\", \"sonarqube-mcp-server@latest\"],\n      \"env\": {\n        \"SONARQUBE_URL\": \"https://your-sonarqube.com\",\n        \"SONARQUBE_USERNAME\": \"your-username\",\n        \"SONARQUBE_PASSWORD\": \"your-password\"\n      }\n    }\n  }\n}\n```\n\nUsing System Passcode:\n```json\n{\n  \"mcpServers\": {\n    \"sonarqube\": {\n      \"command\": \"npx\",\n      \"args\": [\"-y\", \"sonarqube-mcp-server@latest\"],\n      \"env\": {\n        \"SONARQUBE_URL\": \"https://your-sonarqube.com\",\n        \"SONARQUBE_PASSCODE\": \"your-system-passcode\"\n      }\n    }\n  }\n}\n```\n\n\n4. Restart Claude Desktop\n\n### 3. Start Using\n\nAsk Claude to analyze your SonarQube projects:\n\n```\n\"List all my SonarQube projects\"\n\"Show me critical issues in project xyz\"\n\"What's the code coverage for project xyz?\"\n\"Check the quality gate status for project xyz\"\n\"Retrieve security hotspots in project xyz and create a plan to address them\"\n\"Retrieve the issues for pr 123 in project xyz and create a plan to address them\"\n```\n\n## Installation\n\n### NPX (Recommended)\n\nThe simplest way to use the SonarQube MCP Server is through npx:\n\n```json\n{\n  \"mcpServers\": {\n    \"sonarqube\": {\n      \"command\": \"npx\",\n      \"args\": [\"-y\", \"sonarqube-mcp-server@latest\"],\n      \"env\": {\n        \"SONARQUBE_URL\": \"https://sonarqube.example.com\",\n        \"SONARQUBE_TOKEN\": \"your-sonarqube-token\",\n        \"SONARQUBE_ORGANIZATION\": \"your-organization-key\"\n      }\n    }\n  }\n}\n```\n\n### Docker (Recommended for Production)\n\nDocker provides the most reliable deployment method by packaging all dependencies and ensuring consistent behavior across different environments.\n\n> **Enterprise Deployment**: For production deployments with Kubernetes, Helm charts, and cloud-specific configurations, see our comprehensive [Deployment Guide](docs/deployment.md).\n\n#### Quick Start with Docker\n\n**For stdio transport (Claude Desktop):**\n```json\n{\n  \"mcpServers\": {\n    \"sonarqube\": {\n      \"command\": \"docker\",\n      \"args\": [\n        \"run\",\n        \"-i\",\n        \"--rm\",\n        \"-e\", \"SONARQUBE_URL\",\n        \"-e\", \"SONARQUBE_TOKEN\",\n        \"-e\", \"SONARQUBE_ORGANIZATION\",\n        \"sapientpants/sonarqube-mcp-server:latest\"\n      ],\n      \"env\": {\n        \"SONARQUBE_URL\": \"https://sonarqube.example.com\",\n        \"SONARQUBE_TOKEN\": \"your-sonarqube-token\",\n        \"SONARQUBE_ORGANIZATION\": \"your-organization-key\"\n      }\n    }\n  }\n}\n```\n\n\n#### Docker Hub Images\n\nOfficial images are available on Docker Hub: [`sapientpants/sonarqube-mcp-server`](https://hub.docker.com/r/sapientpants/sonarqube-mcp-server)\n\n**Available tags:**\n- `latest` - Latest stable release\n- `1.6.0` - Specific version (recommended for production)\n- `1.6` - Latest patch version of 1.6.x\n- `1` - Latest minor version of 1.x.x\n\n**Pull the image:**\n```bash\ndocker pull sapientpants/sonarqube-mcp-server:latest\n```\n\n#### Advanced Docker Configuration\n\n**With logging enabled:**\n```json\n{\n  \"mcpServers\": {\n    \"sonarqube\": {\n      \"command\": \"docker\",\n      \"args\": [\n        \"run\",\n        \"-i\",\n        \"--rm\",\n        \"-v\", \"/tmp/sonarqube-logs:/logs\",\n        \"-e\", \"SONARQUBE_URL\",\n        \"-e\", \"SONARQUBE_TOKEN\",\n        \"-e\", \"SONARQUBE_ORGANIZATION\",\n        \"-e\", \"LOG_FILE=/logs/sonarqube-mcp.log\",\n        \"-e\", \"LOG_LEVEL=INFO\",\n        \"sapientpants/sonarqube-mcp-server:latest\"\n      ],\n      \"env\": {\n        \"SONARQUBE_URL\": \"https://sonarqube.example.com\",\n        \"SONARQUBE_TOKEN\": \"your-sonarqube-token\",\n        \"SONARQUBE_ORGANIZATION\": \"your-organization-key\"\n      }\n    }\n  }\n}\n```\n\n**Using Docker Compose:**\n```yaml\nversion: '3.8'\nservices:\n  sonarqube-mcp:\n    image: sapientpants/sonarqube-mcp-server:latest\n    environment:\n      - SONARQUBE_URL=https://sonarqube.example.com\n      - SONARQUBE_TOKEN=${SONARQUBE_TOKEN}\n      - SONARQUBE_ORGANIZATION=${SONARQUBE_ORGANIZATION}\n      - LOG_FILE=/logs/sonarqube-mcp.log\n      - LOG_LEVEL=INFO\n    volumes:\n      - ./logs:/logs\n    stdin_open: true\n    tty: true\n```\n\n#### Building Your Own Docker Image\n\nIf you need to customize the server, you can build your own image:\n\n```bash\n# Clone the repository\ngit clone https://github.com/sapientpants/sonarqube-mcp-server.git\ncd sonarqube-mcp-server\n\n# Build the Docker image\ndocker build -t my-sonarqube-mcp-server .\n\n# Run your custom image\ndocker run -i --rm \\\n  -e SONARQUBE_URL=\"https://sonarqube.example.com\" \\\n  -e SONARQUBE_TOKEN=\"your-token\" \\\n  my-sonarqube-mcp-server\n```\n\n#### Docker Best Practices\n\n1. **Version Pinning**: Always use specific version tags in production:\n   ```bash\n   sapientpants/sonarqube-mcp-server:1.6.0\n   ```\n\n2. **Resource Limits**: Set appropriate resource limits:\n   ```bash\n   docker run -i --rm \\\n     --memory=\"256m\" \\\n     --cpus=\"0.5\" \\\n     sapientpants/sonarqube-mcp-server:1.6.0\n   ```\n\n3. **Security**: Run as non-root user (default in our image):\n   ```bash\n   docker run -i --rm \\\n     --user node \\\n     sapientpants/sonarqube-mcp-server:1.6.0\n   ```\n\n4. **Health Checks**: The container includes a health check that verifies the Node.js process is running\n\n### Local Development\n\nFor development or customization:\n\n```json\n{\n  \"mcpServers\": {\n    \"sonarqube\": {\n      \"command\": \"node\",\n      \"args\": [\"/path/to/sonarqube-mcp-server/dist/index.js\"],\n      \"env\": {\n        \"SONARQUBE_URL\": \"https://sonarqube.example.com\",\n        \"SONARQUBE_TOKEN\": \"your-sonarqube-token\",\n        \"SONARQUBE_ORGANIZATION\": \"your-organization-key\"\n      }\n    }\n  }\n}\n```\n\n## Configuration\n\n### Environment Variables\n\n#### Authentication (choose one method)\n\n| Variable | Description | Required | Default |\n|----------|-------------|----------|---------|\n| **Token Authentication** | | | |\n| `SONARQUBE_TOKEN` | Authentication token for SonarQube API access | ✅ Yes* | - |\n| **Basic Authentication** | | | |\n| `SONARQUBE_USERNAME` | Username for Basic authentication | ✅ Yes* | - |\n| `SONARQUBE_PASSWORD` | Password for Basic authentication | ✅ Yes* | - |\n| **System Passcode** | | | |\n| `SONARQUBE_PASSCODE` | System passcode for SonarQube authentication | ✅ Yes* | - |\n\n*One authentication method is required. Token authentication takes priority if multiple methods are configured.\n\n#### Connection Settings\n\n| Variable | Description | Required | Default |\n|----------|-------------|----------|---------|\n| `SONARQUBE_URL` | URL of your SonarQube instance | ❌ No | `https://sonarcloud.io` |\n| `SONARQUBE_ORGANIZATION` | Organization key (required for SonarCloud) | ❌ No** | - |\n| `LOG_FILE` | Path to write log files (e.g., `/tmp/sonarqube-mcp.log`) | ❌ No | - |\n| `LOG_LEVEL` | Minimum log level (DEBUG, INFO, WARN, ERROR) | ❌ No | `DEBUG` |\n\n**Required when using SonarCloud\n\n\n### Authentication Methods\n\nThe server supports three authentication methods, with important differences between SonarQube versions:\n\n#### 1. Token Authentication (Recommended)\n\n**SonarQube 10.0+ (Bearer Token)**\n- Starting with SonarQube 10.0, Bearer token authentication is the recommended approach\n- Most secure and flexible option\n- Tokens can have limited permissions\n- Configuration:\n  ```json\n  {\n    \"env\": {\n      \"SONARQUBE_TOKEN\": \"your-token-here\"\n    }\n  }\n  ```\n\n**SonarQube < 10.0 (Token as Username)**\n- For versions before 10.0, tokens must be sent as the username in Basic authentication\n- No password is required when using a token as username\n- The server automatically handles this based on your SonarQube version\n- Configuration remains the same - just use `SONARQUBE_USERNAME` with the token value:\n  ```json\n  {\n    \"env\": {\n      \"SONARQUBE_USERNAME\": \"your-token-here\"\n    }\n  }\n  ```\n\n#### 2. Basic Authentication\n- Traditional username and password authentication\n- Suitable for self-hosted SonarQube instances\n- May not work with SonarCloud if 2FA is enabled\n- Configuration:\n  ```json\n  {\n    \"env\": {\n      \"SONARQUBE_USERNAME\": \"your-username\",\n      \"SONARQUBE_PASSWORD\": \"your-password\"\n    }\n  }\n  ```\n\n#### 3. System Passcode\n- Special authentication for SonarQube system administration\n- Typically used for automated deployment scenarios\n- Configuration:\n  ```json\n  {\n    \"env\": {\n      \"SONARQUBE_PASSCODE\": \"your-system-passcode\"\n    }\n  }\n  ```\n\n**Note:** Token authentication takes priority if multiple authentication methods are configured. The server will automatically use the appropriate authentication strategy based on your SonarQube version.\n\n### SonarCloud vs SonarQube\n\n**For SonarCloud:**\n- Set `SONARQUBE_URL` to `https://sonarcloud.io`\n- `SONARQUBE_ORGANIZATION` is required\n- Token authentication is recommended\n\n**For SonarQube Server:**\n- Set `SONARQUBE_URL` to your instance URL\n- `SONARQUBE_ORGANIZATION` is typically not needed\n- All authentication methods are supported\n\n\n### Elicitation Configuration (Experimental)\n\nThe server supports interactive user input through MCP's elicitation capability. This feature is opt-in and requires compatible MCP clients.\n\n**Environment Variables:**\n- `SONARQUBE_MCP_ELICITATION`: Set to `true` to enable elicitation\n- `SONARQUBE_MCP_BULK_THRESHOLD`: Number of items before confirmation (default: 5)\n- `SONARQUBE_MCP_REQUIRE_COMMENTS`: Set to `true` to require comments for resolutions\n- `SONARQUBE_MCP_INTERACTIVE_SEARCH`: Set to `true` for interactive disambiguation\n\n**Example Configuration:**\n```json\n{\n  \"mcpServers\": {\n    \"sonarqube\": {\n      \"command\": \"npx\",\n      \"args\": [\"-y\", \"sonarqube-mcp-server@latest\"],\n      \"env\": {\n        \"SONARQUBE_URL\": \"https://sonarcloud.io\",\n        \"SONARQUBE_TOKEN\": \"your-token\",\n        \"SONARQUBE_MCP_ELICITATION\": \"true\",\n        \"SONARQUBE_MCP_BULK_THRESHOLD\": \"10\",\n        \"SONARQUBE_MCP_REQUIRE_COMMENTS\": \"true\"\n      }\n    }\n  }\n}\n```\n\n**Features When Enabled:**\n1. **Bulk Operation Confirmation**: Prompts for confirmation before marking multiple issues\n2. **Comment Collection**: Collects explanatory comments when marking issues as false positive or won't fix\n3. **Authentication Setup**: Guides through authentication setup when credentials are missing\n4. **Search Disambiguation**: Helps select from multiple matching components or projects\n\n**Note:** This feature requires MCP clients that support elicitation. Not all clients may support this capability.\n\n### Logging Configuration\n\nThe server supports file-based logging for debugging and monitoring. Since MCP servers use stdout for protocol communication, logs are written to a file instead of stdout/stderr to avoid interference.\n\n**Enable Logging:**\n```json\n{\n  \"mcpServers\": {\n    \"sonarqube\": {\n      \"command\": \"npx\",\n      \"args\": [\"-y\", \"sonarqube-mcp-server@latest\"],\n      \"env\": {\n        \"SONARQUBE_URL\": \"https://sonarcloud.io\",\n        \"SONARQUBE_TOKEN\": \"your-token-here\",\n        \"SONARQUBE_ORGANIZATION\": \"your-org\",\n        \"LOG_FILE\": \"/tmp/sonarqube-mcp.log\",\n        \"LOG_LEVEL\": \"INFO\"\n      }\n    }\n  }\n}\n```\n\n**Log Levels:**\n- `DEBUG`: Detailed information for debugging\n- `INFO`: General information about server operation\n- `WARN`: Warning events that might lead to issues\n- `ERROR`: Error events (server continues running)\n\n**Example Log Output:**\n```\n2024-01-15T10:30:45.123Z INFO [index] Starting SonarQube MCP server\n2024-01-15T10:30:45.234Z INFO [index] Environment variables validated successfully\n2024-01-15T10:30:45.345Z INFO [index] SonarQube client created successfully\n2024-01-15T10:30:45.456Z INFO [index] SonarQube MCP server started successfully\n2024-01-15T10:30:50.123Z DEBUG [index] Handling SonarQube projects request\n2024-01-15T10:30:50.567Z INFO [index] Successfully retrieved projects {\"count\": 5}\n```\n\n\n## Available Tools\n\n### Permission Requirements\n\nDifferent SonarQube tools require different permission levels:\n\n**Tools requiring Admin permissions:**\n- `projects` - Lists all SonarQube projects with metadata (visibility, lastAnalysisDate, revision)\n\n**Tools accessible to all users:**\n- `components` - Search and navigate projects, directories, and files (requires 'Browse' permission on at least one project)\n- All other tools require appropriate permissions based on the resources being accessed\n\n#### Listing Projects\n\n**For Administrators:**\nUse the `projects` tool to get full project metadata including visibility, last analysis date, and revision info.\n\n**For All Users:**\nUse the `components` tool with project qualifier:\n- \"List all projects I have access to\" → `components` with `qualifiers: ['TRK']`\n- \"Search for projects containing 'mobile'\" → `components` with `query: 'mobile', qualifiers: ['TRK']`\n\nThe `components` tool provides a more accessible alternative for non-admin users to discover projects they have access to.\n\n### Project Management\n\n#### `projects`\nList all SonarQube projects with pagination support.\n\n**Parameters:**\n- `page` (optional): Page number for results pagination\n- `page_size` (optional): Number of items per page\n\n### Metrics and Measures\n\n#### `metrics`\nGet available metrics from SonarQube.\n\n**Parameters:**\n- `page` (optional): Page number for results pagination\n- `page_size` (optional): Number of items per page\n\n#### `measures_component`\nGet measures for a specific component.\n\n**Parameters:**\n- `component` (required): Component key\n- `metric_keys` (required): Array of metric keys\n- `additional_fields` (optional): Additional fields to return\n- `branch` (optional): Branch name\n- `pull_request` (optional): Pull request key\n- `period` (optional): Period index\n\n#### `measures_components`\nGet measures for multiple components.\n\n**Parameters:**\n- `component_keys` (required): Array of component keys\n- `metric_keys` (required): Array of metric keys\n- Additional parameters same as `measures_component`\n- `page` (optional): Page number\n- `page_size` (optional): Items per page\n\n#### `measures_history`\nGet measures history for a component.\n\n**Parameters:**\n- `component` (required): Component key\n- `metrics` (required): Array of metric keys\n- `from` (optional): Start date (YYYY-MM-DD)\n- `to` (optional): End date (YYYY-MM-DD)\n- `branch` (optional): Branch name\n- `pull_request` (optional): Pull request key\n- `page` (optional): Page number\n- `page_size` (optional): Items per page\n\n### Issue Management\n\n#### `issues`\nSearch and filter SonarQube issues by severity, status, assignee, tag, file path, and more. Critical for dashboards, targeted clean-up sprints, security audits, and regression testing. Supports faceted search for aggregations.\n\n**Component/File Path Filters:**\n- `project_key` (optional): Single project key (backward compatible)\n- `projects` (optional): Array of project keys for multi-project analysis\n- `component_keys` (optional): Array of component keys (file paths, directories, or modules) - use this to filter issues by specific files or folders\n- `components` (optional): Alias for component_keys\n- `on_component_only` (optional): Boolean to return only issues on specified components, not sub-components\n\n**Branch/PR Support:**\n- `branch` (optional): Branch name for branch analysis\n- `pull_request` (optional): Pull request ID for PR analysis\n\n**Issue Filters:**\n- `issues` (optional): Array of specific issue keys to retrieve\n- `severity` (optional): Single severity (deprecated, use severities)\n- `severities` (optional): Array of severities (INFO, MINOR, MAJOR, CRITICAL, BLOCKER)\n- `statuses` (optional): Array of statuses (OPEN, CONFIRMED, REOPENED, RESOLVED, CLOSED)\n- `resolutions` (optional): Array of resolutions (FALSE-POSITIVE, WONTFIX, FIXED, REMOVED)\n- `resolved` (optional): Boolean filter for resolved/unresolved\n- `types` (optional): Array of types (CODE_SMELL, BUG, VULNERABILITY, SECURITY_HOTSPOT)\n\n**Clean Code Taxonomy (SonarQube 10.x+):**\n- `clean_code_attribute_categories` (optional): Array (ADAPTABLE, CONSISTENT, INTENTIONAL, RESPONSIBLE)\n- `impact_severities` (optional): Array (HIGH, MEDIUM, LOW)\n- `impact_software_qualities` (optional): Array (MAINTAINABILITY, RELIABILITY, SECURITY)\n- `issue_statuses` (optional): Array of new issue status values\n\n**Rules and Tags:**\n- `rules` (optional): Array of rule keys\n- `tags` (optional): Array of issue tags - essential for security audits, regression testing, and categorized analysis\n\n**Date Filters:**\n- `created_after` (optional): Issues created after date (YYYY-MM-DD)\n- `created_before` (optional): Issues created before date (YYYY-MM-DD)\n- `created_at` (optional): Issues created on date (YYYY-MM-DD)\n- `created_in_last` (optional): Issues created in last period (e.g., \"30d\", \"1m\")\n\n**Assignment:**\n- `assigned` (optional): Boolean filter for assigned/unassigned\n- `assignees` (optional): Array of assignee logins - critical for targeted clean-up sprints and workload analysis\n- `author` (optional): Single author login\n- `authors` (optional): Array of author logins\n\n**Security Standards:**\n- `cwe` (optional): Array of CWE identifiers\n- `owasp_top10` (optional): Array of OWASP Top 10 categories\n- `owasp_top10_v2021` (optional): Array of OWASP Top 10 2021 categories\n- `sans_top25` (optional): Array of SANS Top 25 categories\n- `sonarsource_security` (optional): Array of SonarSource security categories\n- `sonarsource_security_category` (optional): Additional security categories\n\n**Other Filters:**\n- `languages` (optional): Array of programming languages\n- `facets` (optional): Array of facets to aggregate\n- `facet_mode` (optional): Facet aggregation mode ('effort' or 'count')\n- `since_leak_period` (optional): Boolean for leak period filter (deprecated)\n- `in_new_code_period` (optional): Boolean for new code period filter\n\n**Sorting:**\n- `s` (optional): Sort field (e.g., 'SEVERITY', 'CREATION_DATE', 'UPDATE_DATE')\n- `asc` (optional): Boolean for ascending sort direction (default: false)\n\n**Response Control:**\n- `additional_fields` (optional): Array of additional fields to include\n- `page` (optional): Page number for pagination\n- `page_size` (optional): Number of items per page\n\n**Faceted Search (Dashboard Support):**\n- `facets` (optional): Array of facets to compute for aggregations. Available facets: severities, statuses, resolutions, rules, tags, types, authors, assignees, languages, etc.\n- `facet_mode` (optional): Mode for facet computation: 'count' (number of issues) or 'effort' (remediation effort)\n\n**Example Use Cases:**\n\n1. **Dashboard Query** - Get issue counts by severity and assignee:\n```json\n{\n  \"project_key\": \"my-project\",\n  \"facets\": [\"severities\", \"assignees\", \"tags\"],\n  \"facet_mode\": \"count\"\n}\n```\n\n2. **Security Audit** - Find critical security issues in authentication modules:\n```json\n{\n  \"project_key\": \"my-project\",\n  \"component_keys\": [\"src/auth/\", \"src/security/\"],\n  \"tags\": [\"security\", \"vulnerability\"],\n  \"severities\": [\"CRITICAL\", \"BLOCKER\"],\n  \"statuses\": [\"OPEN\", \"REOPENED\"]\n}\n```\n\n3. **Sprint Planning** - Get open issues for specific team members:\n```json\n{\n  \"project_key\": \"my-project\",\n  \"assignees\": [\"john.doe@example.com\", \"jane.smith@example.com\"],\n  \"statuses\": [\"OPEN\", \"CONFIRMED\"],\n  \"facets\": [\"severities\", \"types\"],\n  \"facet_mode\": \"effort\"\n}\n```\n\n4. **File-Specific Analysis** - Issues in a specific file:\n```json\n{\n  \"project_key\": \"my-project\",  \n  \"component_keys\": [\"src/main/java/com/example/PaymentService.java\"],\n  \"on_component_only\": true\n}\n```\n\n### Component Navigation\n\n#### `components`\nSearch and navigate SonarQube components (projects, directories, files). Supports text search, filtering by type/language, and tree navigation.\n\n**Search Parameters:**\n- `query` (optional): Text search query\n- `qualifiers` (optional): Array of component types (TRK, DIR, FIL, UTS, BRC, APP, VW, SVW, LIB)\n- `language` (optional): Programming language filter\n\n**Tree Navigation Parameters:**\n- `component` (optional): Component key for tree navigation\n- `strategy` (optional): Tree traversal strategy ('all', 'children', 'leaves')\n\n**Common Parameters:**\n- `asc` (optional): Sort ascending/descending\n- `ps` (optional): Page size (default: 100, max: 500)\n- `p` (optional): Page number\n- `branch` (optional): Branch name\n- `pullRequest` (optional): Pull request ID\n\n**Component Qualifiers:**\n- `TRK`: Project\n- `DIR`: Directory\n- `FIL`: File\n- `UTS`: Unit Test\n- `BRC`: Branch\n- `APP`: Application\n- `VW`: View\n- `SVW`: Sub-view\n- `LIB`: Library\n\n**Example Use Cases:**\n\n1. **Find specific files:**\n```json\n{\n  \"query\": \"UserService\",\n  \"qualifiers\": [\"FIL\"]\n}\n```\n\n2. **List all test files in a project:**\n```json\n{\n  \"component\": \"my-project\",\n  \"qualifiers\": [\"UTS\"]\n}\n```\n\n3. **Navigate directory structure:**\n```json\n{\n  \"component\": \"my-project:src/main\",\n  \"strategy\": \"children\",\n  \"qualifiers\": [\"DIR\", \"FIL\"]\n}\n```\n\n4. **Search for components by language:**\n```json\n{\n  \"language\": \"java\",\n  \"qualifiers\": [\"FIL\"],\n  \"query\": \"Controller\"\n}\n```\n\n5. **Get project list:**\n```json\n{\n  \"qualifiers\": [\"TRK\"]\n}\n```\n\n### Security Hotspots\n\n#### `hotspots`\nSearch for security hotspots with specialized filters for security review workflows.\n\n**Parameters:**\n- `project_key` (optional): Project key to filter hotspots\n- `branch` (optional): Branch name for branch analysis\n- `pull_request` (optional): Pull request ID for PR analysis\n- `status` (optional): Hotspot status (TO_REVIEW, REVIEWED)\n- `resolution` (optional): Hotspot resolution (FIXED, SAFE)\n- `files` (optional): Array of file paths to filter\n- `assigned_to_me` (optional): Boolean to show only assigned hotspots\n- `since_leak_period` (optional): Boolean for leak period filter\n- `in_new_code_period` (optional): Boolean for new code period filter\n- `page` (optional): Page number for pagination\n- `page_size` (optional): Number of items per page\n\n#### `hotspot`\nGet detailed information about a specific security hotspot including security context.\n\n**Parameters:**\n- `hotspot_key` (required): The unique key of the hotspot\n\n**Returns:**\n- Detailed hotspot information including:\n  - Security category and vulnerability probability\n  - Rule information and security context\n  - Changelog and comments\n  - Code flows and locations\n\n#### `update_hotspot_status`\nUpdate the status of a security hotspot (requires appropriate permissions).\n\n**Parameters:**\n- `hotspot_key` (required): The unique key of the hotspot\n- `status` (required): New status (TO_REVIEW, REVIEWED)\n- `resolution` (optional): Resolution when status is REVIEWED (FIXED, SAFE)\n- `comment` (optional): Comment explaining the status change\n\n### Quality Gates\n\n#### `quality_gates`\nList available quality gates.\n\n**No parameters required**\n\n#### `quality_gate`\nGet quality gate conditions.\n\n**Parameters:**\n- `id` (required): Quality gate ID\n\n#### `quality_gate_status`\nGet project quality gate status.\n\n**Parameters:**\n- `project_key` (required): Project key\n- `branch` (optional): Branch name\n- `pull_request` (optional): Pull request key\n\n### Source Code\n\n#### `source_code`\nView source code with issues highlighted.\n\n**Parameters:**\n- `key` (required): File key\n- `from` (optional): Start line\n- `to` (optional): End line\n- `branch` (optional): Branch name\n- `pull_request` (optional): Pull request key\n\n#### `scm_blame`\nGet SCM blame information for source code.\n\n**Parameters:**\n- Same as `source_code`\n\n### System Monitoring\n\n#### `system_health`\nGet the health status of the SonarQube instance.\n\n**No parameters required**\n\n#### `system_status`\nGet the status of the SonarQube instance.\n\n**No parameters required**\n\n#### `system_ping`\nPing the SonarQube instance to check if it is up.\n\n**No parameters required**\n\n### Issue Resolution and Management\n\n#### `markIssueFalsePositive`\nMark an issue as false positive.\n\n**Parameters:**\n- `issue_key` (required): The key of the issue to mark\n- `comment` (optional): Comment explaining why it's a false positive\n\n#### `markIssueWontFix`\nMark an issue as won't fix.\n\n**Parameters:**\n- `issue_key` (required): The key of the issue to mark\n- `comment` (optional): Comment explaining why it won't be fixed\n\n#### `markIssuesFalsePositive`\nMark multiple issues as false positive in bulk.\n\n**Parameters:**\n- `issue_keys` (required): Array of issue keys to mark\n- `comment` (optional): Comment applying to all issues\n\n#### `markIssuesWontFix`\nMark multiple issues as won't fix in bulk.\n\n**Parameters:**\n- `issue_keys` (required): Array of issue keys to mark\n- `comment` (optional): Comment applying to all issues\n\n#### `addCommentToIssue`\nAdd a comment to a SonarQube issue.\n\n**Parameters:**\n- `issue_key` (required): The key of the issue to comment on\n- `text` (required): The comment text (supports markdown formatting)\n\n#### `assignIssue`\nAssign a SonarQube issue to a user or unassign it.\n\n**Parameters:**\n- `issueKey` (required): The key of the issue to assign\n- `assignee` (optional): Username of the assignee. Leave empty to unassign the issue\n\n**Example usage:**\n```json\n{\n  \"issueKey\": \"PROJECT-123\",\n  \"assignee\": \"john.doe\"\n}\n```\n\n## Usage Examples\n\n### Basic Project Analysis\n```\n\"List all my SonarQube projects\"\n\"Show me the code coverage for project xyz\"\n\"What metrics are available for analysis?\"\n```\n\n### Issue Investigation\n```\n\"Show me all critical bugs in project abc\"\n\"Find security vulnerabilities in the main branch\"\n\"List all code smells created in the last week\"\n\"Show unresolved issues assigned to john.doe\"\n\"Analyze issues in the feature/new-login branch\"\n\"Compare issues between main and develop branches\"\n\"Find issues across multiple projects: proj1, proj2, proj3\"\n\"Show me issues sorted by severity in descending order\"\n\"Find all issues with clean code impact on reliability\"\n```\n\n### Component Navigation\n```\n\"Find all files containing 'UserService' in their name\"\n\"List all test files in my project\"\n\"Show me the directory structure of src/main\"\n\"Find all Java controller files\"\n\"List all projects in SonarQube\"\n\"Navigate to the authentication module\"\n\"Search for TypeScript files in the frontend directory\"\n\"Show me all directories under src/components\"\n```\n\n### Issue Management\n```\n\"Assign issue PROJECT-123 to john.doe\"\n\"Unassign issue PROJECT-456\"\n\"Mark issue ABC-789 as false positive with comment: 'Test code only'\"\n\"Add comment to issue XYZ-111: 'Fixed in commit abc123'\"\n\"Bulk mark issues DEF-222, DEF-223 as won't fix\"\n```\n\n### Quality Monitoring\n```\n\"Check the quality gate status for my main project\"\n\"Show me the code coverage history for the last month\"\n\"What are the quality gate conditions?\"\n\"Compare metrics between develop and main branches\"\n```\n\n### Security Hotspot Review\n```\n\"Find all security hotspots that need review in project xyz\"\n\"Show me hotspots in the authentication module\"\n\"Get details for hotspot HSP-12345\"\n\"List all hotspots assigned to me\"\n\"Mark hotspot HSP-12345 as safe with explanation\"\n\"Find hotspots in the new code period\"\n\"Show security hotspots in pull request #42\"\n```\n\n### Source Code Analysis\n```\n\"Show me the source code for file xyz with issues highlighted\"\n\"Get blame information for the problematic file\"\n\"View issues in the authentication module\"\n```\n\n### System Health\n```\n\"Check if SonarQube is running\"\n\"What's the health status of the SonarQube instance?\"\n\"Show me the system status\"\n```\n\n## Architecture\n\nThe SonarQube MCP Server follows a modular architecture:\n\n```\n┌─────────────────┐     ┌──────────────────┐     ┌─────────────────┐\n│  Claude Desktop │────▶│  MCP Server      │────▶│  SonarQube API  │\n│  (MCP Client)   │◀────│  (index.ts)      │◀────│                 │\n└─────────────────┘     └──────────────────┘     └─────────────────┘\n                               │\n                               ▼\n                        ┌──────────────────┐\n                        │  SonarQube       │\n                        │  Client          │\n                        │  (sonarqube.ts)  │\n                        └──────────────────┘\n                               │\n                               ▼\n                        ┌──────────────────┐\n                        │  API Module      │\n                        │  (api.ts)        │\n                        └──────────────────┘\n```\n\n### Key Components\n\n1. **MCP Server (`index.ts`)**: Main entry point that initializes the MCP server and registers all available tools\n2. **SonarQube Client (`sonarqube.ts`)**: Handles business logic and parameter transformation\n3. **API Module (`api.ts`)**: Manages HTTP requests to the SonarQube API\n4. **Type Definitions**: TypeScript interfaces for type safety\n\n### Data Flow\n\n1. MCP clients make requests through registered tools\n2. Tool handlers validate and transform parameters\n3. SonarQube client methods process the requests\n4. API module executes HTTP requests\n5. Responses are formatted and returned to the client\n\n## Development\n\n### Prerequisites\n\n- Node.js 20 or higher\n- pnpm 10.7.0 or higher\n- Docker (for container builds)\n\n### Setup\n\n1. Clone the repository:\n```bash\ngit clone https://github.com/sapientpants/sonarqube-mcp-server.git\ncd sonarqube-mcp-server\n```\n\n2. Install dependencies:\n```bash\npnpm install\n```\n\n3. Build the project:\n```bash\npnpm build\n```\n\n### Development Commands\n\n```bash\n# Install dependencies\npnpm install\n\n# Build the project\npnpm build\n\n# Run in development mode with auto-reload\npnpm dev\n\n# Run tests\npnpm test\n\n# Run tests with coverage\npnpm test:coverage\n\n# Lint the code\npnpm lint\n\n# Fix linting issues\npnpm lint:fix\n\n# Check types\npnpm check-types\n\n# Format code\npnpm format\n\n# Run all validations\npnpm validate\n\n# Inspect MCP schema\npnpm inspect\n```\n\n### Testing\n\nThe project uses Jest for testing with:\n- Unit tests for all major components\n- Mocked HTTP responses using `nock`\n- Coverage reporting\n- TypeScript support\n\nRun specific test files:\n```bash\nNODE_ENV=test NODE_OPTIONS='--experimental-vm-modules --no-warnings' jest src/__tests__/file-name.test.ts\n```\n\n### Code Quality\n\nThe project maintains high code quality through:\n- TypeScript for type safety\n- ESLint for code linting\n- Prettier for code formatting\n- Jest for testing\n- SonarCloud for continuous code analysis\n\n## Troubleshooting\n\n### Common Issues\n\n#### \"Authentication failed\"\n- **Cause**: Invalid or expired token\n- **Solution**: Generate a new token in SonarQube/SonarCloud\n\n#### \"Project not found\"\n- **Cause**: Incorrect project key or insufficient permissions\n- **Solution**: Verify the project key and check token permissions\n\n#### \"Organization required\"\n- **Cause**: Using SonarCloud without organization parameter\n- **Solution**: Add `SONARQUBE_ORGANIZATION` to your configuration\n\n#### \"Connection refused\"\n- **Cause**: Incorrect URL or network issues\n- **Solution**: Verify `SONARQUBE_URL` and network connectivity\n\n#### \"No output or errors visible\"\n- **Cause**: Errors might be happening but not visible in Claude Desktop\n- **Solution**: Enable logging with `LOG_FILE` and check the log file for detailed error messages\n\n\n### FAQ\n\n**Q: Can I use this with both SonarQube and SonarCloud?**\nA: Yes! Set the appropriate `SONARQUBE_URL` and include `SONARQUBE_ORGANIZATION` for SonarCloud.\n\n**Q: What permissions does my token need?**\nA: The token needs \"Execute Analysis\" permission and access to the projects you want to analyze.\n\n**Q: How do I filter issues by multiple criteria?**\nA: The `issues` tool supports extensive filtering. You can combine multiple parameters like severity, type, status, and date ranges.\n\n**Q: Can I analyze pull requests?**\nA: Yes! Many tools support `branch` and `pull_request` parameters for branch and PR analysis.\n\n## Troubleshooting\n\n### Common Error Messages and Solutions\n\n#### Authentication Errors\n\n**Error: \"Authentication failed\"**\n- **Solution**: Check that your SONARQUBE_TOKEN is valid and not expired. Generate a new token from your SonarQube user profile.\n\n**Error: \"No SonarQube authentication configured\"**\n- **Solution**: Set one of the following authentication methods:\n  - `SONARQUBE_TOKEN` for token-based authentication (recommended)\n  - `SONARQUBE_USERNAME` and `SONARQUBE_PASSWORD` for basic authentication\n  - `SONARQUBE_PASSCODE` for system passcode authentication\n\n#### Authorization Errors\n\n**Error: \"Access denied\"**\n- **Solution**: Ensure your token has the required permissions for the operation. Common required permissions:\n  - \"Execute Analysis\" for code analysis\n  - \"Browse\" for reading project data\n  - \"Administer Issues\" for issue management operations\n\n#### Resource Not Found Errors\n\n**Error: \"Resource not found\"**\n- **Solution**: Verify that:\n  - The project key/component exists in SonarQube\n  - You have access to the resource\n  - The URL path is correct (no typos in project keys)\n\n#### Network and Connection Errors\n\n**Error: \"Connection refused\"**\n- **Solution**: Check that:\n  - The SonarQube server is running\n  - The SONARQUBE_URL is correct\n  - There are no firewall rules blocking the connection\n\n**Error: \"Network error\" or timeout errors**\n- **Solution**: \n  - Verify your network connection\n  - Check if the SonarQube server is accessible\n  - Ensure the URL doesn't have a trailing slash\n  - For self-hosted instances, verify SSL certificates\n\n#### Rate Limiting\n\n**Error: \"Rate limit exceeded\"**\n- **Solution**: The server automatically retries rate-limited requests with exponential backoff. If you continue to hit rate limits:\n  - Reduce the frequency of your requests\n  - Implement request batching where possible\n  - Contact your SonarQube administrator to increase rate limits\n\n#### Configuration Errors\n\n**Error: \"Invalid SONARQUBE_URL\"**\n- **Solution**: Provide a valid URL including the protocol:\n  - ✅ Correct: `https://sonarcloud.io`\n  - ✅ Correct: `https://sonarqube.example.com`\n  - ❌ Wrong: `sonarcloud.io` (missing protocol)\n  - ❌ Wrong: `https://sonarqube.example.com/` (trailing slash)\n\n### Debugging Tips\n\n1. **Enable Debug Logging**:\n   ```bash\n   export LOG_LEVEL=DEBUG\n   ```\n\n2. **Check Environment Variables**:\n   ```bash\n   echo $SONARQUBE_URL\n   echo $SONARQUBE_TOKEN\n   echo $SONARQUBE_ORGANIZATION\n   ```\n\n3. **Test Connection**:\n   Use the `ping` tool to verify connectivity:\n   ```bash\n   # In your MCP client\n   sonarqube.ping\n   ```\n\n4. **Verify Permissions**:\n   Use the `projects` tool to list accessible projects:\n   ```bash\n   # In your MCP client\n   sonarqube.projects\n   ```\n\n### Retry Behavior\n\nThe server automatically retries failed requests for transient errors:\n- **Network errors**: Retried up to 3 times\n- **Rate limiting**: Retried with exponential backoff\n- **Server errors (5xx)**: Retried up to 3 times\n\nRetry delays: 1s → 2s → 4s (capped at 10s)\n\n### Getting Help\n\nIf you continue to experience issues:\n\n1. Check the [GitHub Issues](https://github.com/sapientpants/sonarqube-mcp-server/issues) for similar problems\n2. Enable debug logging and collect error details\n3. Create a new issue with:\n   - Error messages\n   - Environment details (OS, Node version)\n   - SonarQube version\n   - Steps to reproduce\n\n## Contributing\n\nWe welcome contributions! Please see our [Contributing Guidelines](CONTRIBUTING.md) for details.\n\n### How to Contribute\n\n1. Fork the repository\n2. Create a feature branch (`git checkout -b feature/amazing-feature`)\n3. Commit your changes (`git commit -m 'Add amazing feature'`)\n4. Push to the branch (`git push origin feature/amazing-feature`)\n5. Open a Pull Request\n\n### Development Guidelines\n\n- Write tests for new features\n- Update documentation as needed\n- Follow the existing code style\n- Ensure all tests pass\n- Add appropriate error handling\n\n## License\n\nThis project is licensed under the MIT License - see the [LICENSE](LICENSE) file for details.\n\n## External Resources\n\n### SonarQube Documentation\n- [SonarQube Documentation](https://docs.sonarqube.org/latest/)\n- [SonarCloud Documentation](https://docs.sonarcloud.io/)\n- [Web API Documentation](https://docs.sonarqube.org/latest/extend/web-api/)\n\n### Model Context Protocol\n- [MCP Documentation](https://modelcontextprotocol.io/)\n- [MCP Specification](https://github.com/modelcontextprotocol/specification)\n- [MCP TypeScript SDK](https://github.com/modelcontextprotocol/typescript-sdk)\n\n---\n\n<p align=\"center\">\n  Made with ❤️ by the SonarQube MCP Server community\n</p>\n",
  "category": "AI Tools",
  "quality_score": 68,
  "archestra_config": {
    "client_config_permutations": {
      "mcpServers": {
        "sonarqube-mcp-server-token-auth": {
          "command": "npx",
          "args": ["-y", "sonarqube-mcp-server@latest"],
          "env": {
            "SONARQUBE_URL": "https://sonarcloud.io",
            "SONARQUBE_TOKEN": "your-token-here",
            "SONARQUBE_ORGANIZATION": "your-org (for SonarCloud)"
          }
        },
        "sonarqube-mcp-server-basic-auth": {
          "command": "npx",
          "args": ["-y", "sonarqube-mcp-server@latest"],
          "env": {
            "SONARQUBE_URL": "https://your-sonarqube.com",
            "SONARQUBE_USERNAME": "your-username",
            "SONARQUBE_PASSWORD": "your-password"
          }
        },
        "sonarqube-mcp-server-passcode-auth": {
          "command": "npx",
          "args": ["-y", "sonarqube-mcp-server@latest"],
          "env": {
            "SONARQUBE_URL": "https://your-sonarqube.com",
            "SONARQUBE_PASSCODE": "your-system-passcode"
          }
        },
        "sapientpants-sonarqube-mcp-server-docker": {
          "command": "docker",
          "args": [
            "run",
            "-i",
            "--rm",
            "-e",
            "SONARQUBE_URL",
            "-e",
            "SONARQUBE_TOKEN",
            "-e",
            "SONARQUBE_ORGANIZATION",
            "sapientpants/sonarqube-mcp-server:latest"
          ],
          "env": {
            "SONARQUBE_URL": "https://sonarqube.example.com",
            "SONARQUBE_TOKEN": "your-sonarqube-token",
            "SONARQUBE_ORGANIZATION": "your-organization-key"
          }
        }
      }
    },
    "oauth": {
      "provider": null,
      "required": false
    }
  },
  "github_info": {
    "owner": "sapientpants",
    "repo": "sonarqube-mcp-server",
    "url": "https://github.com/sapientpants/sonarqube-mcp-server",
    "name": "sonarqube-mcp-server",
    "path": null,
    "stars": 77,
    "contributors": 2,
    "issues": 0,
    "releases": true,
    "ci_cd": true,
    "latest_commit_hash": "5cb7896da6651d0c019ed5d34b989911f7a1d16e"
  },
  "programming_language": "TypeScript",
  "framework": null,
  "last_scraped_at": "2025-08-04T09:36:24.104Z",
  "evaluation_model": "gemini-2.5-flash",
  "protocol_features": {
    "implementing_tools": true,
    "implementing_prompts": false,
    "implementing_resources": true,
    "implementing_sampling": true,
    "implementing_roots": false,
    "implementing_logging": true,
    "implementing_stdio": true,
    "implementing_streamable_http": false,
    "implementing_oauth2": false
  },
  "dependencies": [
    {
      "name": "@modelcontextprotocol/sdk",
      "importance": 10
    },
    {
      "name": "lodash",
      "importance": 4
    },
    {
      "name": "opossum",
      "importance": 8
    },
    {
      "name": "sonarqube-web-api-client",
      "importance": 9
    },
    {
      "name": "zod",
      "importance": 7
    },
    {
      "name": "zod-to-json-schema",
      "importance": 5
    }
  ],
  "raw_dependencies": "=== package.json ===\n{\n  \"name\": \"sonarqube-mcp-server\",\n  \"version\": \"1.7.3\",\n  \"description\": \"Model Context Protocol server for SonarQube\",\n  \"type\": \"module\",\n  \"main\": \"dist/index.js\",\n  \"types\": \"dist/index.d.ts\",\n  \"bin\": {\n    \"sonarqube-mcp-server\": \"./dist/index.js\"\n  },\n  \"exports\": {\n    \".\": {\n      \"import\": \"./dist/index.js\",\n      \"types\": \"./dist/index.d.ts\"\n    }\n  },\n  \"repository\": {\n    \"type\": \"git\",\n    \"url\": \"git+https://github.com/sapientpants/sonarqube-mcp-server.git\"\n  },\n  \"bugs\": {\n    \"url\": \"https://github.com/sapientpants/sonarqube-mcp-server/issues\"\n  },\n  \"scripts\": {\n    \"build\": \"tsc\",\n    \"ci\": \"pnpm audit --audit-level=low && pnpm run format:check && pnpm run lint && pnpm run check-types && pnpm run build && pnpm run test:coverage\",\n    \"start\": \"node --experimental-specifier-resolution=node dist/index.js\",\n    \"dev\": \"ts-node-dev --respawn --transpile-only src/index.ts\",\n    \"watch\": \"tsc -w\",\n    \"test\": \"NODE_ENV=test NODE_OPTIONS='--experimental-vm-modules --no-warnings' jest --detectOpenHandles --forceExit\",\n    \"test:watch\": \"NODE_ENV=test NODE_OPTIONS='--experimental-vm-modules --no-warnings' jest --watch --detectOpenHandles --forceExit\",\n    \"test:coverage\": \"NODE_ENV=test NODE_OPTIONS='--experimental-vm-modules --no-warnings' jest --coverage --detectOpenHandles --forceExit\",\n    \"lint\": \"eslint . --ext .ts\",\n    \"lint:fix\": \"eslint . --ext .ts --fix\",\n    \"format\": \"prettier --write \\\"src/**/*.ts\\\"\",\n    \"format:check\": \"prettier --check \\\"src/**/*.ts\\\"\",\n    \"check-types\": \"tsc --noEmit\",\n    \"prepare\": \"husky\",\n    \"validate\": \"pnpm run check-types && pnpm run lint && pnpm run test\",\n    \"inspect\": \"npx @modelcontextprotocol/inspector@latest node dist/index.js\",\n    \"clean\": \"rm -rf dist\"\n  },\n  \"lint-staged\": {\n    \"*.{ts,tsx}\": [\n      \"prettier --check\",\n      \"eslint\"\n    ]\n  },\n  \"keywords\": [\n    \"sonarqube\",\n    \"mcp\",\n    \"model-context-protocol\"\n  ],\n  \"author\": \"Marc Tremblay <marc.tremblay@gmail.com>\",\n  \"homepage\": \"https://github.com/sapientpants/sonarqube-mcp-server\",\n  \"license\": \"MIT\",\n  \"packageManager\": \"pnpm@10.7.1\",\n  \"dependencies\": {\n    \"@modelcontextprotocol/sdk\": \"^1.17.0\",\n    \"lodash\": \"^4.17.21\",\n    \"opossum\": \"^9.0.0\",\n    \"sonarqube-web-api-client\": \"0.11.1\",\n    \"zod\": \"^3.25.76\",\n    \"zod-to-json-schema\": \"^3.24.6\"\n  },\n  \"devDependencies\": {\n    \"@eslint/js\": \"^9.32.0\",\n    \"@jest/globals\": \"^30.0.5\",\n    \"@types/jest\": \"^30.0.0\",\n    \"@types/lodash\": \"^4.17.20\",\n    \"@types/node\": \"^24.1.0\",\n    \"@types/opossum\": \"^8.1.9\",\n    \"@typescript-eslint/eslint-plugin\": \"^8.38.0\",\n    \"@typescript-eslint/parser\": \"^8.38.0\",\n    \"eslint\": \"^9.32.0\",\n    \"eslint-config-prettier\": \"^10.1.8\",\n    \"eslint-plugin-prettier\": \"^5.5.3\",\n    \"husky\": \"^9.1.7\",\n    \"jest\": \"^30.0.5\",\n    \"lint-staged\": \"^16.1.2\",\n    \"nock\": \"^14.0.7\",\n    \"prettier\": \"^3.6.2\",\n    \"supertest\": \"^7.1.4\",\n    \"ts-jest\": \"^29.4.0\",\n    \"ts-node\": \"^10.9.2\",\n    \"ts-node-dev\": \"^2.0.0\",\n    \"typescript\": \"^5.8.3\"\n  },\n  \"pnpm\": {\n    \"overrides\": {\n      \"brace-expansion@1\": \">=1.1.12\",\n      \"brace-expansion@2\": \">=2.0.2\",\n      \"brace-expansion\": \">=4.0.0\",\n      \"cross-spawn\": \">=7.0.5\",\n      \"form-data\": \">=4.0.4\",\n      \"@eslint/plugin-kit\": \">=0.3.3\"\n    },\n    \"ignoredBuiltDependencies\": [\n      \"bcrypt\"\n    ]\n  }\n}\n"
}
