{
  "name": "go  mysql",
  "slug": "zhwt__go-mcp-mysql",
  "description": "Zero burden, ready-to-use Model Context Protocol (MCP) server for interacting with MySQL and automation. No Node.js or Python environment needed.",
  "readme": "# go-mcp-mysql\n\n## Overview\n\nZero burden, ready-to-use Model Context Protocol (MCP) server for interacting with MySQL and automation. No Node.js or Python environment needed. This server provides tools to do CRUD operations on MySQL databases and tables, and a read-only mode to prevent surprise write operations. You can also make the MCP server check the query plan by using a `EXPLAIN` statement before executing the query by adding a `--with-explain-check` flag.\n\nPlease note that this is a work in progress and may not yet be ready for production use.\n\n## Installation\n\n1. Get the latest [release](https://github.com/Zhwt/go-mcp-mysql/releases) and put it in your `$PATH` or somewhere you can easily access.\n\n2. Or if you have Go installed, you can build it from source:\n\n```sh\ngo install -v github.com/Zhwt/go-mcp-mysql@latest\n```\n\n## Usage\n\n### Method A: Using Command Line Arguments\n\n```json\n{\n  \"mcpServers\": {\n    \"mysql\": {\n      \"command\": \"go-mcp-mysql\",\n      \"args\": [\n        \"--host\", \"localhost\",\n        \"--user\", \"root\",\n        \"--pass\", \"password\",\n        \"--port\", \"3306\",\n        \"--db\", \"mydb\"\n      ]\n    }\n  }\n}\n```\n\n### Method B: Using DSN With Custom Options\n\n```json\n{\n  \"mcpServers\": {\n    \"mysql\": {\n      \"command\": \"go-mcp-mysql\",\n      \"args\": [\n        \"--dsn\", \"username:password@tcp(localhost:3306)/mydb?parseTime=true&loc=Local\"\n      ]\n    }\n  }\n}\n```\n\nPlease refer to [MySQL DSN](https://github.com/go-sql-driver/mysql#dsn-data-source-name) for more details.\n\nNote: For those who put the binary outside of your `$PATH`, you need to replace `go-mcp-mysql` with the full path to the binary: e.g.: if you put the binary in the **Downloads** folder, you may use the following path:\n\n```json\n{\n  \"mcpServers\": {\n    \"mysql\": {\n      \"command\": \"C:\\\\Users\\\\<username>\\\\Downloads\\\\go-mcp-mysql.exe\",\n      \"args\": [\n        ...\n      ]\n    }\n  }\n}\n```\n\n### Optional Flags\n\n- Add a `--read-only` flag to enable read-only mode. In this mode, only tools beginning with `list`, `read_` and `desc_` are available. Make sure to refresh/restart the MCP server after adding this flag.\n- By default, CRUD queries will be first executed with a `EXPLAIN ?` statement to check whether the generated query plan matches the expected pattern. Add a `--with-explain-check` flag to disable this behavior.\n\n## Tools\n\n### Schema Tools\n\n1. `list_database`\n\n    - List all databases in the MySQL server.\n    - Parameters: None\n    - Returns: A list of matching database names.\n\n2. `list_table`\n\n    - List all tables in the MySQL server.\n    - Parameters:\n        - `name`: If provided, list tables with the specified name, same as SQL `SHOW TABLES LIKE '%name%'`. Otherwise, list all tables.\n    - Returns: A list of matching table names.\n\n3. `create_table`\n\n    - Create a new table in the MySQL server.\n    - Parameters:\n        - `query`: The SQL query to create the table.\n    - Returns: x rows affected.\n\n4. `alter_table`\n\n    - Alter an existing table in the MySQL server. The LLM is informed not to drop an existing table or column.\n    - Parameters:\n        - `query`: The SQL query to alter the table.\n    - Returns: x rows affected.\n\n5. `desc_table`\n\n    - Describe the structure of a table.\n    - Parameters:\n        - `name`: The name of the table to describe.\n    - Returns: The structure of the table.\n\n### Data Tools\n\n1. `read_query`\n\n    - Execute a read-only SQL query.\n    - Parameters:\n        - `query`: The SQL query to execute.\n    - Returns: The result of the query.\n\n2. `write_query`\n\n    - Execute a write SQL query.\n    - Parameters:\n        - `query`: The SQL query to execute.\n    - Returns: x rows affected, last insert id: <last_insert_id>.\n\n3. `update_query`\n\n    - Execute an update SQL query.\n    - Parameters:\n        - `query`: The SQL query to execute.\n    - Returns: x rows affected.\n\n4. `delete_query`\n\n    - Execute a delete SQL query.\n    - Parameters:\n        - `query`: The SQL query to execute.\n    - Returns: x rows affected.\n\n## License\n\nMIT\n",
  "category": "Development",
  "qualityScore": 53,
  "githubUrl": "https://github.com/Zhwt/go-mcp-mysql",
  "programmingLanguage": "Go",
  "gitHubOrg": "Zhwt",
  "gitHubRepo": "go-mcp-mysql",
  "repositoryPath": null,
  "gh_stars": 39,
  "gh_contributors": 2,
  "gh_issues": 0,
  "gh_releases": true,
  "gh_ci_cd": false,
  "gh_latest_commit_hash": "e343dd15fac0ba9dfaab4ce33c894638a22c7db1",
  "last_scraped_at": "2025-08-03T19:52:59.227Z",
  "implementing_tools": true,
  "implementing_prompts": false,
  "implementing_resources": true,
  "implementing_sampling": false,
  "implementing_roots": false,
  "implementing_logging": false,
  "implementing_stdio": true,
  "implementing_streamable_http": false,
  "implementing_oauth2": false,
  "rawDependencies": "=== go.mod ===\nmodule github.com/Zhwt/go-mcp-mysql\n\ngo 1.23.1\n\nrequire (\n\tgithub.com/go-sql-driver/mysql v1.9.1\n\tgithub.com/jmoiron/sqlx v1.4.0\n\tgithub.com/mark3labs/mcp-go v0.18.0\n)\n\nrequire (\n\tfilippo.io/edwards25519 v1.1.0 // indirect\n\tgithub.com/DATA-DOG/go-sqlmock v1.5.2 // indirect\n\tgithub.com/davecgh/go-spew v1.1.1 // indirect\n\tgithub.com/google/uuid v1.6.0 // indirect\n\tgithub.com/pmezard/go-difflib v1.0.0 // indirect\n\tgithub.com/stretchr/testify v1.10.0 // indirect\n\tgithub.com/yosida95/uritemplate/v3 v3.0.2 // indirect\n\tgopkg.in/yaml.v3 v3.0.1 // indirect\n)\n",
  "evaluation_model": "gemini-2.5-flash",
  "configForClients": {
    "mcpServers": {
      "go-mcp-mysql-args": {
        "command": "go-mcp-mysql",
        "args": [
          "--host",
          "localhost",
          "--user",
          "root",
          "--pass",
          "password",
          "--port",
          "3306",
          "--db",
          "mydb"
        ]
      },
      "go-mcp-mysql-dsn": {
        "command": "go-mcp-mysql",
        "args": [
          "--dsn",
          "username:password@tcp(localhost:3306)/mydb?parseTime=true&loc=Local"
        ]
      },
      "go-mcp-mysql-args-read-only": {
        "command": "go-mcp-mysql",
        "args": [
          "--host",
          "localhost",
          "--user",
          "root",
          "--pass",
          "password",
          "--port",
          "3306",
          "--db",
          "mydb",
          "--read-only"
        ]
      },
      "go-mcp-mysql-dsn-read-only": {
        "command": "go-mcp-mysql",
        "args": [
          "--dsn",
          "username:password@tcp(localhost:3306)/mydb?parseTime=true&loc=Local",
          "--read-only"
        ]
      },
      "go-mcp-mysql-args-with-explain-check": {
        "command": "go-mcp-mysql",
        "args": [
          "--host",
          "localhost",
          "--user",
          "root",
          "--pass",
          "password",
          "--port",
          "3306",
          "--db",
          "mydb",
          "--with-explain-check"
        ]
      },
      "go-mcp-mysql-dsn-with-explain-check": {
        "command": "go-mcp-mysql",
        "args": [
          "--dsn",
          "username:password@tcp(localhost:3306)/mydb?parseTime=true&loc=Local",
          "--with-explain-check"
        ]
      }
    }
  },
  "configForArchestra": {
    "oauth": {},
    "server_config": {
      "args": [
        "--host",
        "localhost",
        "--user",
        "root",
        "--pass",
        "password",
        "--port",
        "3306",
        "--db",
        "mydb"
      ],
      "command": "go-mcp-mysql",
      "transport": "stdio",
      "env": {}
    }
  },
  "dependencies": [
    {
      "importance": 10,
      "name": "mark3labs/mcp-go"
    },
    {
      "importance": 9,
      "name": "go-sql-driver/mysql"
    },
    {
      "importance": 8,
      "name": "jmoiron/sqlx"
    }
  ]
}